nomad_camels_driver_keithley_197a/__init__.py
nomad_camels_driver_keithley_197a/keithley_197a.py
nomad_camels_driver_keithley_197a/keithley_197a_ophyd.py
nomad_camels_driver_keithley_197a-0.1.0.dist-info/METADATA
nomad_camels_driver_keithley_197a-0.1.0.dist-info/WHEEL
nomad_camels_driver_keithley_197a-0.1.0.dist-info/top_level.txt
nomad_camels_driver_keithley_197a-0.1.0.dist-info/RECORD
